pipeline/__init__.py
pipeline/data_manipulation.py
pipeline/pipeline.py
tests/__init__.py
tests/test_pipeline.py
superseeker-0.1.dist-info/LICENSE
superseeker-0.1.dist-info/METADATA
superseeker-0.1.dist-info/WHEEL
superseeker-0.1.dist-info/entry_points.txt
superseeker-0.1.dist-info/top_level.txt
superseeker-0.1.dist-info/RECORD
