Metadata-Version: 2.1
Name: superseeker
Version: 0.1
Summary: SuperSeeker_Pipeline is a Python library for identifying subclonal evolution in cancer.
Home-page: https://github.com/gageblack/superseeker_pipeline
Author: Gage Black
Author-email: gage.black@utah.edu
License: MIT
Classifier: Programming Language :: Python :: 3
Classifier: Operating System :: OS Independent
Requires-Python: >=3.6
License-File: LICENSE
Requires-Dist: numpy
Requires-Dist: pandas
